clr/__init__.py
clr/style_builder.py
clr-1.0.3.dist-info/DESCRIPTION.rst
clr-1.0.3.dist-info/METADATA
clr-1.0.3.dist-info/RECORD
clr-1.0.3.dist-info/WHEEL
clr-1.0.3.dist-info/metadata.json
clr-1.0.3.dist-info/top_level.txt
