Metadata-Version: 1.0
Name: clr
Version: 1.0.3
Summary: 🌈 Terminal string styling
Home-page: https://github.com/lmittmann/clr
Author: lmittmann
Author-email: UNKNOWN
License: MIT
Keywords: clr,color,ansi,terminal styling,chalk
Platform: UNKNOWN
